LICENSE
README.md
pyproject.toml
src/endstone_plugin/__init__.py
src/endstone_plugin.egg-info/PKG-INFO
src/endstone_plugin.egg-info/SOURCES.txt
src/endstone_plugin.egg-info/dependency_links.txt
src/endstone_plugin.egg-info/entry_points.txt
src/endstone_plugin.egg-info/requires.txt
src/endstone_plugin.egg-info/top_level.txt