Metadata-Version: 2.1
Name: endstone-plugin
Version: 0.1.0
Summary: Official Python plugin template for Endstone servers
Author-email: Endstone Developers <hello@endstone.dev>
Maintainer-email: Vincent Wu <magicdroidx@gmail.com>, Endstone Developers <hello@endstone.dev>
License: MIT License
Project-URL: Homepage, https://github.com/EndstoneMC/python-plugin-template
Project-URL: Documentation, https://readthedocs.org
Project-URL: Repository, https://github.com/EndstoneMC/python-plugin-template.git
Project-URL: Issues, https://github.com/EndstoneMC/python-plugin-template/issues
Project-URL: Changelog, https://github.com/EndstoneMC/python-plugin-template/blob/main/CHANGELOG.md
Keywords: endstone,plugin
Classifier: Development Status :: 3 - Alpha
Classifier: Programming Language :: Python
Requires-Python: >=3.9
License-File: LICENSE
Requires-Dist: endstone
